LICENSE.txt
README.rst
setup.py
becke/AtomicData.py
becke/CheckpointFile.py
becke/ERIs.py
becke/GaussianBasis.py
becke/GaussianIntegrals.py
becke/Ints1e.py
becke/LebedevQuadrature.py
becke/MulticenterIntegration.py
becke/SphericalCoords.py
becke/SphericalHarmonics.py
becke/__init__.py
becke/lebedev_quad_points.py
becke/settings.py
becke_multicenter_integration.egg-info/PKG-INFO
becke_multicenter_integration.egg-info/SOURCES.txt
becke_multicenter_integration.egg-info/dependency_links.txt
becke_multicenter_integration.egg-info/not-zip-safe
becke_multicenter_integration.egg-info/requires.txt
becke_multicenter_integration.egg-info/top_level.txt