Metadata-Version: 2.1
Name: becke-multicenter-integration
Version: 0.0.2
Summary: Molecular integrals on multicenter grids (Becke's integration scheme)
Home-page: https://github.com/humeniuka/becke_multicenter_integration
Author: Alexander Humeniuk
Author-email: alexander.humeniuk@gmail.com
License: LICENSE.txt
Platform: UNKNOWN
Classifier: Development Status :: 4 - Beta
Classifier: Environment :: Console
Classifier: Intended Audience :: Science/Research
Classifier: Intended Audience :: Education
Classifier: Intended Audience :: Developers
Classifier: License :: OSI Approved :: MIT License
Classifier: Operating System :: POSIX :: Linux
Classifier: Programming Language :: Python :: 3.7
Classifier: Topic :: Scientific/Engineering :: Chemistry
Classifier: Topic :: Scientific/Engineering :: Physics
Classifier: Topic :: Software Development :: Libraries :: Python Modules
License-File: LICENSE.txt
